CHANGES.rst
LICENSE.rst
MANIFEST.in
README.rst
buildout.cfg
setup.py
travis.cfg
src/collective/__init__.py
src/collective.navigationtitle.egg-info/PKG-INFO
src/collective.navigationtitle.egg-info/SOURCES.txt
src/collective.navigationtitle.egg-info/dependency_links.txt
src/collective.navigationtitle.egg-info/entry_points.txt
src/collective.navigationtitle.egg-info/namespace_packages.txt
src/collective.navigationtitle.egg-info/not-zip-safe
src/collective.navigationtitle.egg-info/requires.txt
src/collective.navigationtitle.egg-info/top_level.txt
src/collective/navigationtitle/__init__.py
src/collective/navigationtitle/behavior.py
src/collective/navigationtitle/behavior.zcml
src/collective/navigationtitle/configure.zcml
src/collective/navigationtitle/indexer.py
src/collective/navigationtitle/indexer.zcml
src/collective/navigationtitle/interfaces.py
src/collective/navigationtitle/navigation.py
src/collective/navigationtitle/setuphandlers.py
src/collective/navigationtitle/testing.py
src/collective/navigationtitle/locales/collective.navigationtitle.pot
src/collective/navigationtitle/locales/plone-manual.pot
src/collective/navigationtitle/locales/update.sh
src/collective/navigationtitle/locales/de/LC_MESSAGES/collective.navigationtitle.po
src/collective/navigationtitle/locales/de/LC_MESSAGES/plone.po
src/collective/navigationtitle/profiles/default/browserlayer.xml
src/collective/navigationtitle/profiles/default/catalog.xml
src/collective/navigationtitle/profiles/default/collectivenavigationtitle_marker.txt
src/collective/navigationtitle/profiles/default/metadata.xml
src/collective/navigationtitle/tests/__init__.py
src/collective/navigationtitle/tests/test_robot.py
src/collective/navigationtitle/tests/test_setup.py
src/collective/navigationtitle/tests/robot/test_example.robot