Metadata-Version: 1.1
Name: collective.navigationtitle
Version: 0.2
Summary: An add-on for Plone that allows to add a title that is used in navigation elements.
Home-page: https://bluedynamics.com
Author: BlueDynamics Alliance
Author-email: dev@bluedynamics.com
License: GNU General Public Licence
Keywords: Python Plone Dexterity
Platform: UNKNOWN
Classifier: Environment :: Web Environment
Classifier: Framework :: Plone
Classifier: Programming Language :: Python
Classifier: Programming Language :: Python :: 2.7
Classifier: License :: OSI Approved :: GNU General Public License (GPL)
Classifier: Operating System :: OS Independent
